GoogleIt/__init__.py
GoogleIt/converter.py
GoogleIt/googleit.py
GoogleIt/models.py
GoogleIt/text_processor.py
GoogleIt-2.0.2.dist-info/LICENSE
GoogleIt-2.0.2.dist-info/METADATA
GoogleIt-2.0.2.dist-info/WHEEL
GoogleIt-2.0.2.dist-info/top_level.txt
GoogleIt-2.0.2.dist-info/RECORD
