Metadata-Version: 2.1
Name: GoogleIt
Version: 2.0.2
Summary: The GoogleIt Python package offers a versatile set of tools for querying Google search results, downloading content, preprocessing text, converting HTML to PDF, and leveraging Google Palm 2 and Gemini language models for natural language processing tasks.
Home-page: https://github.com/william-renaldy/GoogleIt
Author: William Renaldy A
Author-email: williamrenaldy.a@gmail.com
Project-URL: Bug Tracker, https://github.com/william-renaldy/GoogleIt/issues
Classifier: Programming Language :: Python :: 3
Classifier: License :: OSI Approved :: MIT License
Classifier: Operating System :: OS Independent
Requires-Python: >=3.9
License-File: LICENSE
Requires-Dist: beautifulsoup4 >=4.12.2
Requires-Dist: docx >=0.2.4
Requires-Dist: nltk >=3.8
Requires-Dist: pdf2docx >=0.5.6
Requires-Dist: protobuf >=4.25.1
Requires-Dist: PyPDF2 >=3.0.1
Requires-Dist: python-docx >=0.8.11
Requires-Dist: requests >=2.28.2
Requires-Dist: scikit-learn >=1.3.2
Requires-Dist: selenium >=4.16.0
